{"error": null, "message": "Requested completed successfully.", "payload": [{"ts": 1559563800, "lt": 48.1165, "ln": -122.7504, "s": 0, "h": 314, "stat": "active", "dtg": "30.86", "dstat": "Racing"}, {"ts": 1559564400, "lt": 48.1164, "ln": -122.7504, "s": 0.1, "h": 172, "stat": "active", "dtg": "30.86", "dstat": "Racing"}, {"ts": 1559565000, "lt": 48.1155, "ln": -122.7507, "s": 0.3, "h": 193, "stat": "active", "dtg": "30.86", "dstat": "Racing"}, {"ts": 1559565600, "lt": 48.1163, "ln": -122.7504, "s": 0.3, "h": 15, "stat": "active", "dtg": "30.87", "dstat": "Racing"}, {"ts": 1559566200, "lt": 48.1165, "ln": -122.7504, "s": 0.1, "h": 355, "stat": "active", "dtg": "30.86", "dstat": "Racing"}, {"ts": 1559602800, "lt": 48.1164, "ln": -122.7504, "s": 0, "h": 233, "stat": "active", "dtg": "30.86", "dstat": "Racing"}, {"ts": 1559603400, "lt": 48.1164, "ln": -122.7504, "s": 0, "h": 243, "stat": "active", "dtg": "30.86", "dstat": "Racing"}, {"ts": 1559604000, "lt": 48.1164, "ln": -122.7504, "s": 0, "h": 82, "stat": "active", "dtg": "30.86", "dstat": "Racing"}, {"ts": 1559604600, "lt": 48.1164, "ln": -122.7504, "s": 0, "h": 299, "stat": "active", "dtg": "30.86", "dstat": "Racing"}, {"ts": 1559605200, "lt": 48.1164, "ln": -122.7504, "s": 0, "h": 89, "stat": "active", "dtg": "30.86", "dstat": "Racing"}, {"ts": 1559605800, "lt": 48.1164, "ln": -122.7504, "s": 0, "h": 65, "stat": "active", "dtg": "30.86", "dstat": "Racing"}, {"ts": 1559606400, "lt": 48.1164, "ln": -122.7504, "s": 0, "h": 338, "stat": "active", "dtg": "30.86", "dstat": "Racing"}, {"ts": 1559607000, "lt": 48.1164, "ln": -122.7504, "s": 0, "h": 203, "stat": "active", "dtg": "30.86", "dstat": "Racing"}, {"ts": 1559607600, "lt": 48.1164, "ln": -122.7504, "s": 0, "h": 63, "stat": "active", "dtg": "30.86", "dstat": "Racing"}, {"ts": 1559608200, "lt": 48.1164, "ln": -122.7504, "s": 0, "h": 180, "stat": "active", "dtg": "30.86", "dstat": "Racing"}, {"ts": 1559608800, "lt": 48.1164, "ln": -122.7504, "s": 0, "h": 279, "stat": "active", "dtg": "30.86", "dstat": "Racing"}, {"ts": 1559609400, "lt": 48.1164, "ln": -122.7504, "s": 0, "h": 125, "stat": "active", "dtg": "30.86", "dstat": "Racing"}, {"ts": 1559610000, "lt": 48.1164, "ln": -122.7504, "s": 0, "h": 329, "stat": "active", "dtg": "30.86", "dstat": "Racing"}, {"ts": 1559610600, "lt": 48.1164, "ln": -122.7504, "s": 0, "h": 64, "stat": "active", "dtg": "30.86", "dstat": "Racing"}, {"ts": 1559648400, "lt": 48.1162, "ln": -122.7489, "s": 1, "h": 100, "stat": "active", "dtg": "30.86", "dstat": "Racing"}, {"ts": 1559649000, "lt": 48.1168, "ln": -122.743, "s": 1.4, "h": 82, "stat": "active", "dtg": "31.04", "dstat": "Racing"}, {"ts": 1559649600, "lt": 48.1165, "ln": -122.7402, "s": 0.7, "h": 98, "stat": "active", "dtg": "31.16", "dstat": "Racing"}, {"ts": 1559650200, "lt": 48.1159, "ln": -122.7387, "s": 0.4, "h": 120, "stat": "active", "dtg": "31.23", "dstat": "Racing"}, {"ts": 1559650800, "lt": 48.1201, "ln": -122.7388, "s": 1.5, "h": 359, "stat": "active", "dtg": "31.27", "dstat": "Racing"}, {"ts": 1559651400, "lt": 48.138, "ln": -122.7417, "s": 6.5, "h": 353, "stat": "active", "dtg": "30.71", "dstat": "Racing"}, {"ts": 1559652000, "lt": 48.1539, "ln": -122.7503, "s": 6.1, "h": 340, "stat": "active", "dtg": "29.87", "dstat": "Racing"}, {"ts": 1559652600, "lt": 48.1605, "ln": -122.7609, "s": 3.5, "h": 313, "stat": "active", "dtg": "29.04", "dstat": "Racing"}, {"ts": 1559653200, "lt": 48.1639, "ln": -122.7756, "s": 3.8, "h": 289, "stat": "active", "dtg": "28.78", "dstat": "Racing"}, {"ts": 1559653800, "lt": 48.1613, "ln": -122.7891, "s": 3.4, "h": 253, "stat": "active", "dtg": "28.05", "dstat": "Racing"}, {"ts": 1559654400, "lt": 48.1486, "ln": -122.8014, "s": 5.5, "h": 212, "stat": "active", "dtg": "28.05", "dstat": "Racing"}, {"ts": 1559655000, "lt": 48.1479, "ln": -122.816, "s": 3.5, "h": 266, "stat": "active", "dtg": "28.02", "dstat": "Racing"}, {"ts": 1559655600, "lt": 48.1547, "ln": -122.8323, "s": 4.6, "h": 301, "stat": "active", "dtg": "27.04", "dstat": "Racing"}, {"ts": 1559656200, "lt": 48.1445, "ln": -122.8413, "s": 4.3, "h": 210, "stat": "active", "dtg": "26.94", "dstat": "Racing"}, {"ts": 1559656800, "lt": 48.1508, "ln": -122.8626, "s": 5.6, "h": 293, "stat": "active", "dtg": "26.46", "dstat": "Racing"}, {"ts": 1559657400, "lt": 48.1565, "ln": -122.8834, "s": 5.4, "h": 292, "stat": "active", "dtg": "25.55", "dstat": "Racing"}, {"ts": 1559658000, "lt": 48.1635, "ln": -122.901, "s": 4.9, "h": 300, "stat": "active", "dtg": "24.75", "dstat": "Racing"}, {"ts": 1559658600, "lt": 48.1742, "ln": -122.9187, "s": 5.8, "h": 312, "stat": "active", "dtg": "23.87", "dstat": "Racing"}, {"ts": 1559659200, "lt": 48.1868, "ln": -122.9365, "s": 6.2, "h": 316, "stat": "active", "dtg": "22.81", "dstat": "Racing"}, {"ts": 1559659800, "lt": 48.2035, "ln": -122.9398, "s": 6.1, "h": 352, "stat": "active", "dtg": "22.08", "dstat": "Racing"}, {"ts": 1559660400, "lt": 48.2179, "ln": -122.9558, "s": 6.5, "h": 323, "stat": "active", "dtg": "21.13", "dstat": "Racing"}, {"ts": 1559661000, "lt": 48.2313, "ln": -122.9763, "s": 6.9, "h": 314, "stat": "active", "dtg": "20.02", "dstat": "Racing"}, {"ts": 1559661600, "lt": 48.2464, "ln": -122.9954, "s": 7.1, "h": 319, "stat": "active", "dtg": "18.89", "dstat": "Racing"}, {"ts": 1559662200, "lt": 48.2617, "ln": -123.0126, "s": 6.9, "h": 323, "stat": "active", "dtg": "17.76", "dstat": "Racing"}, {"ts": 1559662800, "lt": 48.2727, "ln": -123.0261, "s": 5.1, "h": 320, "stat": "active", "dtg": "16.42", "dstat": "Racing"}, {"ts": 1559663400, "lt": 48.2748, "ln": -123.0294, "s": 1.1, "h": 312, "stat": "active", "dtg": "16.23", "dstat": "Racing"}, {"ts": 1559664000, "lt": 48.2575, "ln": -123.0364, "s": 6.4, "h": 195, "stat": "active", "dtg": "16.59", "dstat": "Racing"}, {"ts": 1559664600, "lt": 48.2407, "ln": -123.0461, "s": 6.5, "h": 200, "stat": "active", "dtg": "16.91", "dstat": "Racing"}, {"ts": 1559665200, "lt": 48.2383, "ln": -123.0536, "s": 2, "h": 244, "stat": "active", "dtg": "16.84", "dstat": "Racing"}, {"ts": 1559665800, "lt": 48.2541, "ln": -123.0721, "s": 7.2, "h": 322, "stat": "active", "dtg": "15.67", "dstat": "Racing"}, {"ts": 1559666400, "lt": 48.2687, "ln": -123.0911, "s": 7, "h": 319, "stat": "active", "dtg": "14.53", "dstat": "Racing"}, {"ts": 1559667000, "lt": 48.2848, "ln": -123.11, "s": 7.4, "h": 321, "stat": "active", "dtg": "13.34", "dstat": "Racing"}, {"ts": 1559667600, "lt": 48.3006, "ln": -123.1294, "s": 7.3, "h": 320, "stat": "active", "dtg": "12.15", "dstat": "Racing"}, {"ts": 1559668200, "lt": 48.315, "ln": -123.1484, "s": 6.9, "h": 318, "stat": "active", "dtg": "11.04", "dstat": "Racing"}, {"ts": 1559668800, "lt": 48.3269, "ln": -123.1688, "s": 6.5, "h": 311, "stat": "active", "dtg": "9.91", "dstat": "Racing"}, {"ts": 1559669400, "lt": 48.3152, "ln": -123.1733, "s": 4.3, "h": 194, "stat": "active", "dtg": "10.10", "dstat": "Racing"}, {"ts": 1559670000, "lt": 48.2992, "ln": -123.1763, "s": 5.8, "h": 187, "stat": "active", "dtg": "10.79", "dstat": "Racing"}, {"ts": 1559670600, "lt": 48.3079, "ln": -123.1997, "s": 6.4, "h": 299, "stat": "active", "dtg": "9.78", "dstat": "Racing"}, {"ts": 1559671200, "lt": 48.3176, "ln": -123.226, "s": 7.2, "h": 298, "stat": "active", "dtg": "8.64", "dstat": "Racing"}, {"ts": 1559671800, "lt": 48.3259, "ln": -123.2525, "s": 7, "h": 295, "stat": "active", "dtg": "7.58", "dstat": "Racing"}, {"ts": 1559672400, "lt": 48.3345, "ln": -123.2816, "s": 7.7, "h": 293, "stat": "active", "dtg": "6.45", "dstat": "Racing"}, {"ts": 1559673000, "lt": 48.342, "ln": -123.3098, "s": 7.3, "h": 291, "stat": "active", "dtg": "5.45", "dstat": "Racing"}, {"ts": 1559673600, "lt": 48.353, "ln": -123.335, "s": 7.3, "h": 303, "stat": "active", "dtg": "4.52", "dstat": "Racing"}, {"ts": 1559674200, "lt": 48.3662, "ln": -123.3555, "s": 6.8, "h": 314, "stat": "active", "dtg": "3.53", "dstat": "Racing"}, {"ts": 1559674800, "lt": 48.3811, "ln": -123.3675, "s": 6.1, "h": 331, "stat": "active", "dtg": "2.58", "dstat": "Racing"}, {"ts": 1559675400, "lt": 48.3931, "ln": -123.379, "s": 5.1, "h": 327, "stat": "active", "dtg": "1.86", "dstat": "Racing"}, {"ts": 1559676000, "lt": 48.4037, "ln": -123.3876, "s": 4.4, "h": 331, "stat": "active", "dtg": "1.32", "dstat": "Racing"}, {"ts": 1559676600, "lt": 48.412, "ln": -123.3944, "s": 3.4, "h": 331, "stat": "active", "dtg": "1.14", "dstat": "Racing"}, {"ts": 1559677200, "lt": 48.4191, "ln": -123.393, "s": 2.6, "h": 7, "stat": "active", "dtg": "0.94", "dstat": "Racing"}, {"ts": 1559677800, "lt": 48.4239, "ln": -123.3862, "s": 2.4, "h": 42, "stat": "active", "dtg": "0.70", "dstat": "Racing"}, {"ts": 1559678400, "lt": 48.4242, "ln": -123.3772, "s": 2.2, "h": 87, "stat": "active", "dtg": "0.36", "dstat": "Racing"}, {"ts": 1559679000, "lt": 48.4227, "ln": -123.3719, "s": 1.4, "h": 113, "stat": "active", "dtg": "0.13", "dstat": "Racing"}, {"ts": 1559679600, "lt": 48.4218, "ln": -123.3698, "s": 0.6, "h": 123, "stat": "active", "dtg": "0.04", "dstat": "Racing"}, {"ts": 1559680200, "lt": 48.4218, "ln": -123.3696, "s": 0.1, "h": 87, "stat": "active", "dtg": "0.05", "dstat": "Racing"}, {"ts": 1559680800, "lt": 48.4218, "ln": -123.3696, "s": 0, "h": 11, "stat": "active", "dtg": "0.05", "dstat": "Finished"}, {"ts": 1559681400, "lt": 48.4218, "ln": -123.3696, "s": 0, "h": 141, "stat": "active", "dtg": "0.05", "dstat": "Finished"}, {"ts": 1559682000, "lt": 48.4218, "ln": -123.3696, "s": 0, "h": 141, "stat": "active", "dtg": "0.05", "dstat": "Finished"}, {"ts": 1559682600, "lt": 48.4218, "ln": -123.3696, "s": 0, "h": 141, "stat": "active", "dtg": "0.05", "dstat": "Finished"}, {"ts": 1559683200, "lt": 48.4218, "ln": -123.3696, "s": 0, "h": 290, "stat": "active", "dtg": "0.05", "dstat": "Finished"}, {"ts": 1559683800, "lt": 48.4217, "ln": -123.3695, "s": 0.1, "h": 116, "stat": "active", "dtg": "0.05", "dstat": "Finished"}, {"ts": 1559684400, "lt": 48.4217, "ln": -123.3695, "s": 0, "h": 262, "stat": "active", "dtg": "0.05", "dstat": "Finished"}, {"ts": 1559685000, "lt": 48.4218, "ln": -123.3696, "s": 0, "h": 278, "stat": "active", "dtg": "0.05", "dstat": "Finished"}, {"ts": 1559685600, "lt": 48.4218, "ln": -123.3696, "s": 0, "h": 355, "stat": "active", "dtg": "0.05", "dstat": "Finished"}, {"ts": 1559686200, "lt": 48.4218, "ln": -123.3696, "s": 0, "h": 355, "stat": "active", "dtg": "0.05", "dstat": "Finished"}, {"ts": 1559686800, "lt": 48.4218, "ln": -123.3696, "s": 0, "h": 168, "stat": "active", "dtg": "0.05", "dstat": "Finished"}], "meta": {"source": "db", "next_update": 0, "query_timestamp": 1572798000}}