{"error": null, "message": "Requested completed successfully.", "payload": [{"ts": 1528762800, "lt": 47.2448, "ln": -122.4329, "s": 0, "h": 134, "stat": "active", "dtg": "Active", "dstat": "Active"}, {"ts": 1528763400, "lt": 47.2444, "ln": -122.4325, "s": 0.2, "h": 151, "stat": "active", "dtg": "53.84", "dstat": "Racing"}, {"ts": 1528764000, "lt": 47.251, "ln": -122.4331, "s": 2.4, "h": 356, "stat": "active", "dtg": "53.75", "dstat": "Racing"}, {"ts": 1528764600, "lt": 47.2598, "ln": -122.4368, "s": 3.3, "h": 344, "stat": "active", "dtg": "53.20", "dstat": "Racing"}, {"ts": 1528765200, "lt": 47.2669, "ln": -122.4441, "s": 3.1, "h": 325, "stat": "active", "dtg": "52.69", "dstat": "Racing"}, {"ts": 1528765800, "lt": 47.2732, "ln": -122.4527, "s": 3.1, "h": 317, "stat": "active", "dtg": "52.21", "dstat": "Racing"}, {"ts": 1528766400, "lt": 47.2799, "ln": -122.4645, "s": 3.7, "h": 309, "stat": "active", "dtg": "51.75", "dstat": "Racing"}, {"ts": 1528767000, "lt": 47.2862, "ln": -122.4752, "s": 3.5, "h": 311, "stat": "active", "dtg": "51.25", "dstat": "Racing"}, {"ts": 1528767600, "lt": 47.2938, "ln": -122.4862, "s": 3.8, "h": 315, "stat": "active", "dtg": "50.78", "dstat": "Racing"}, {"ts": 1528768200, "lt": 47.3019, "ln": -122.4984, "s": 4.1, "h": 314, "stat": "active", "dtg": "50.21", "dstat": "Racing"}, {"ts": 1528768800, "lt": 47.3078, "ln": -122.5099, "s": 3.5, "h": 307, "stat": "active", "dtg": "49.73", "dstat": "Racing"}, {"ts": 1528769400, "lt": 47.3099, "ln": -122.5196, "s": 2.5, "h": 288, "stat": "active", "dtg": "49.40", "dstat": "Racing"}, {"ts": 1528770000, "lt": 47.32, "ln": -122.5231, "s": 3.7, "h": 346, "stat": "active", "dtg": "48.99", "dstat": "Racing"}, {"ts": 1528770600, "lt": 47.3295, "ln": -122.5257, "s": 3.5, "h": 349, "stat": "active", "dtg": "48.31", "dstat": "Racing"}, {"ts": 1528771200, "lt": 47.3376, "ln": -122.5236, "s": 3, "h": 10, "stat": "active", "dtg": "47.82", "dstat": "Racing"}, {"ts": 1528771800, "lt": 47.3382, "ln": -122.5235, "s": 0.2, "h": 10, "stat": "active", "dtg": "47.61", "dstat": "Racing"}, {"ts": 1528772400, "lt": 47.3431, "ln": -122.5243, "s": 1.8, "h": 353, "stat": "active", "dtg": "47.61", "dstat": "Racing"}, {"ts": 1528773000, "lt": 47.3481, "ln": -122.5252, "s": 1.8, "h": 353, "stat": "active", "dtg": "47.61", "dstat": "Racing"}, {"ts": 1528773600, "lt": 47.3531, "ln": -122.526, "s": 1.8, "h": 353, "stat": "active", "dtg": "47.61", "dstat": "Racing"}, {"ts": 1528774200, "lt": 47.3581, "ln": -122.5269, "s": 1.8, "h": 353, "stat": "active", "dtg": "47.61", "dstat": "Racing"}, {"ts": 1528774800, "lt": 47.3631, "ln": -122.5278, "s": 1.8, "h": 353, "stat": "active", "dtg": "47.61", "dstat": "Racing"}, {"ts": 1528775400, "lt": 47.3681, "ln": -122.5286, "s": 1.8, "h": 353, "stat": "active", "dtg": "47.61", "dstat": "Racing"}, {"ts": 1528776000, "lt": 47.3776, "ln": -122.5282, "s": 3.4, "h": 1, "stat": "active", "dtg": "45.40", "dstat": "Racing"}, {"ts": 1528776600, "lt": 47.3906, "ln": -122.528, "s": 4.7, "h": 0, "stat": "active", "dtg": "44.64", "dstat": "Racing"}, {"ts": 1528777200, "lt": 47.3989, "ln": -122.5266, "s": 3, "h": 6, "stat": "active", "dtg": "44.01", "dstat": "Racing"}, {"ts": 1528777800, "lt": 47.4002, "ln": -122.5263, "s": 0.5, "h": 10, "stat": "active", "dtg": "44.01", "dstat": "Racing"}, {"ts": 1528778400, "lt": 47.4068, "ln": -122.5244, "s": 2.5, "h": 11, "stat": "active", "dtg": "44.01", "dstat": "Racing"}, {"ts": 1528779000, "lt": 47.4135, "ln": -122.5224, "s": 2.5, "h": 11, "stat": "active", "dtg": "44.01", "dstat": "Racing"}, {"ts": 1528779600, "lt": 47.4201, "ln": -122.5205, "s": 2.5, "h": 11, "stat": "active", "dtg": "44.01", "dstat": "Racing"}, {"ts": 1528780200, "lt": 47.4267, "ln": -122.5186, "s": 2.5, "h": 11, "stat": "active", "dtg": "44.01", "dstat": "Racing"}, {"ts": 1528780800, "lt": 47.4334, "ln": -122.5167, "s": 2.5, "h": 11, "stat": "active", "dtg": "44.01", "dstat": "Racing"}, {"ts": 1528781400, "lt": 47.44, "ln": -122.5148, "s": 2.5, "h": 11, "stat": "active", "dtg": "44.01", "dstat": "Racing"}, {"ts": 1528782000, "lt": 47.4466, "ln": -122.5129, "s": 2.5, "h": 11, "stat": "active", "dtg": "44.01", "dstat": "Racing"}, {"ts": 1528782600, "lt": 47.4533, "ln": -122.511, "s": 2.5, "h": 11, "stat": "active", "dtg": "44.01", "dstat": "Racing"}, {"ts": 1528783200, "lt": 47.4599, "ln": -122.5091, "s": 2.5, "h": 11, "stat": "active", "dtg": "44.01", "dstat": "Racing"}, {"ts": 1528783800, "lt": 47.4616, "ln": -122.5086, "s": 0.6, "h": 11, "stat": "active", "dtg": "40.50", "dstat": "Racing"}, {"ts": 1528784400, "lt": 47.4669, "ln": -122.5091, "s": 1.9, "h": 356, "stat": "active", "dtg": "40.32", "dstat": "Racing"}, {"ts": 1528785000, "lt": 47.4751, "ln": -122.5087, "s": 2.9, "h": 1, "stat": "active", "dtg": "39.84", "dstat": "Racing"}, {"ts": 1528785600, "lt": 47.4795, "ln": -122.5098, "s": 1.6, "h": 350, "stat": "active", "dtg": "39.58", "dstat": "Racing"}, {"ts": 1528786200, "lt": 47.4875, "ln": -122.508, "s": 2.9, "h": 8, "stat": "active", "dtg": "39.12", "dstat": "Racing"}, {"ts": 1528786800, "lt": 47.4958, "ln": -122.5048, "s": 3.1, "h": 14, "stat": "active", "dtg": "38.66", "dstat": "Racing"}, {"ts": 1528787400, "lt": 47.5027, "ln": -122.5005, "s": 2.7, "h": 22, "stat": "active", "dtg": "38.32", "dstat": "Racing"}, {"ts": 1528788000, "lt": 47.5092, "ln": -122.4958, "s": 2.6, "h": 25, "stat": "active", "dtg": "37.90", "dstat": "Racing"}, {"ts": 1528788600, "lt": 47.5119, "ln": -122.4945, "s": 1, "h": 18, "stat": "active", "dtg": "37.84", "dstat": "Racing"}, {"ts": 1528789200, "lt": 47.5185, "ln": -122.4916, "s": 2.5, "h": 16, "stat": "active", "dtg": "37.84", "dstat": "Racing"}, {"ts": 1528789800, "lt": 47.5252, "ln": -122.4887, "s": 2.5, "h": 16, "stat": "active", "dtg": "37.84", "dstat": "Racing"}, {"ts": 1528790400, "lt": 47.5318, "ln": -122.4857, "s": 2.5, "h": 16, "stat": "active", "dtg": "37.84", "dstat": "Racing"}, {"ts": 1528791000, "lt": 47.5384, "ln": -122.4828, "s": 2.5, "h": 16, "stat": "active", "dtg": "37.84", "dstat": "Racing"}, {"ts": 1528791600, "lt": 47.54, "ln": -122.4821, "s": 0.6, "h": 16, "stat": "active", "dtg": "36.25", "dstat": "Racing"}, {"ts": 1528792200, "lt": 47.54, "ln": -122.4821, "s": 0, "h": 22, "stat": "active", "dtg": "36.24", "dstat": "Racing"}, {"ts": 1528792800, "lt": 47.5437, "ln": -122.482, "s": 1.3, "h": 1, "stat": "active", "dtg": "36.24", "dstat": "Racing"}, {"ts": 1528793400, "lt": 47.5481, "ln": -122.4819, "s": 1.6, "h": 1, "stat": "active", "dtg": "36.24", "dstat": "Racing"}, {"ts": 1528794000, "lt": 47.5526, "ln": -122.4817, "s": 1.6, "h": 1, "stat": "active", "dtg": "36.24", "dstat": "Racing"}, {"ts": 1528794600, "lt": 47.557, "ln": -122.4816, "s": 1.6, "h": 1, "stat": "active", "dtg": "36.24", "dstat": "Racing"}, {"ts": 1528795200, "lt": 47.5614, "ln": -122.4815, "s": 1.6, "h": 1, "stat": "active", "dtg": "36.24", "dstat": "Racing"}, {"ts": 1528795800, "lt": 47.5659, "ln": -122.4813, "s": 1.6, "h": 1, "stat": "active", "dtg": "36.24", "dstat": "Racing"}, {"ts": 1528796400, "lt": 47.5714, "ln": -122.4799, "s": 2, "h": 9, "stat": "active", "dtg": "34.48", "dstat": "Racing"}, {"ts": 1528797000, "lt": 47.5768, "ln": -122.4772, "s": 2, "h": 18, "stat": "active", "dtg": "34.22", "dstat": "Racing"}, {"ts": 1528797600, "lt": 47.5829, "ln": -122.4782, "s": 2.2, "h": 354, "stat": "active", "dtg": "33.86", "dstat": "Racing"}, {"ts": 1528798200, "lt": 47.5878, "ln": -122.4815, "s": 1.9, "h": 335, "stat": "active", "dtg": "33.54", "dstat": "Racing"}, {"ts": 1528798800, "lt": 47.5932, "ln": -122.4866, "s": 2.3, "h": 327, "stat": "active", "dtg": "33.17", "dstat": "Racing"}, {"ts": 1528799400, "lt": 47.5998, "ln": -122.4919, "s": 2.7, "h": 331, "stat": "active", "dtg": "32.73", "dstat": "Racing"}, {"ts": 1528800000, "lt": 47.6078, "ln": -122.4956, "s": 3.1, "h": 343, "stat": "active", "dtg": "32.23", "dstat": "Racing"}, {"ts": 1528800600, "lt": 47.6157, "ln": -122.4983, "s": 2.9, "h": 346, "stat": "active", "dtg": "31.71", "dstat": "Racing"}, {"ts": 1528801200, "lt": 47.618, "ln": -122.5009, "s": 1, "h": 321, "stat": "active", "dtg": "31.55", "dstat": "Racing"}, {"ts": 1528801800, "lt": 47.6176, "ln": -122.5024, "s": 0.4, "h": 246, "stat": "active", "dtg": "31.55", "dstat": "Racing"}, {"ts": 1528802400, "lt": 47.6176, "ln": -122.5024, "s": 0, "h": 0, "stat": "active", "dtg": "31.55", "dstat": "Racing"}, {"ts": 1528815000, "lt": 47.7031, "ln": -122.5064, "s": 0, "h": 296, "stat": "active", "dtg": "26.67", "dstat": "Racing"}, {"ts": 1528815600, "lt": 47.7031, "ln": -122.5064, "s": 0, "h": 89, "stat": "active", "dtg": "26.67", "dstat": "Racing"}, {"ts": 1528816200, "lt": 47.7031, "ln": -122.5062, "s": 0.1, "h": 100, "stat": "active", "dtg": "26.67", "dstat": "Racing"}, {"ts": 1528816800, "lt": 47.7057, "ln": -122.503, "s": 1.2, "h": 39, "stat": "active", "dtg": "26.58", "dstat": "Racing"}, {"ts": 1528817400, "lt": 47.7125, "ln": -122.4976, "s": 2.8, "h": 28, "stat": "active", "dtg": "26.28", "dstat": "Racing"}, {"ts": 1528818000, "lt": 47.7181, "ln": -122.4931, "s": 2.3, "h": 29, "stat": "active", "dtg": "26.05", "dstat": "Racing"}, {"ts": 1528818600, "lt": 47.7243, "ln": -122.4886, "s": 2.5, "h": 25, "stat": "active", "dtg": "25.94", "dstat": "Racing"}, {"ts": 1528819200, "lt": 47.7298, "ln": -122.4827, "s": 2.5, "h": 35, "stat": "active", "dtg": "25.58", "dstat": "Racing"}, {"ts": 1528819800, "lt": 47.7364, "ln": -122.477, "s": 2.8, "h": 29, "stat": "active", "dtg": "25.32", "dstat": "Racing"}, {"ts": 1528820400, "lt": 47.742, "ln": -122.4749, "s": 2.1, "h": 14, "stat": "active", "dtg": "25.05", "dstat": "Racing"}, {"ts": 1528821000, "lt": 47.7469, "ln": -122.4727, "s": 1.9, "h": 16, "stat": "active", "dtg": "24.83", "dstat": "Racing"}, {"ts": 1528821600, "lt": 47.7523, "ln": -122.4691, "s": 2.2, "h": 24, "stat": "active", "dtg": "24.64", "dstat": "Racing"}, {"ts": 1528822200, "lt": 47.7581, "ln": -122.4685, "s": 2.1, "h": 3, "stat": "active", "dtg": "24.31", "dstat": "Racing"}, {"ts": 1528822800, "lt": 47.764, "ln": -122.4693, "s": 2.2, "h": 355, "stat": "active", "dtg": "24.00", "dstat": "Racing"}, {"ts": 1528823400, "lt": 47.7691, "ln": -122.4721, "s": 2, "h": 339, "stat": "active", "dtg": "23.66", "dstat": "Racing"}, {"ts": 1528824000, "lt": 47.7726, "ln": -122.4763, "s": 1.6, "h": 320, "stat": "active", "dtg": "23.41", "dstat": "Racing"}, {"ts": 1528824600, "lt": 47.7775, "ln": -122.4801, "s": 2, "h": 332, "stat": "active", "dtg": "23.07", "dstat": "Racing"}, {"ts": 1528825200, "lt": 47.7826, "ln": -122.4831, "s": 2, "h": 338, "stat": "active", "dtg": "22.75", "dstat": "Racing"}, {"ts": 1528825800, "lt": 47.7865, "ln": -122.488, "s": 1.9, "h": 319, "stat": "active", "dtg": "22.44", "dstat": "Racing"}, {"ts": 1528826400, "lt": 47.7947, "ln": -122.4919, "s": 3.1, "h": 342, "stat": "active", "dtg": "21.96", "dstat": "Racing"}, {"ts": 1528827000, "lt": 47.7974, "ln": -122.4937, "s": 1.1, "h": 334, "stat": "active", "dtg": "21.74", "dstat": "Racing"}, {"ts": 1528827600, "lt": 47.7988, "ln": -122.4929, "s": 0.5, "h": 21, "stat": "active", "dtg": "21.73", "dstat": "Racing"}, {"ts": 1528828200, "lt": 47.801, "ln": -122.4913, "s": 0.9, "h": 25, "stat": "active", "dtg": "21.73", "dstat": "Racing"}, {"ts": 1528828800, "lt": 47.8032, "ln": -122.4897, "s": 0.9, "h": 25, "stat": "active", "dtg": "21.73", "dstat": "Racing"}, {"ts": 1528829400, "lt": 47.8054, "ln": -122.4882, "s": 0.9, "h": 25, "stat": "active", "dtg": "21.73", "dstat": "Racing"}, {"ts": 1528830000, "lt": 47.8076, "ln": -122.4866, "s": 0.9, "h": 25, "stat": "active", "dtg": "21.73", "dstat": "Racing"}, {"ts": 1528830600, "lt": 47.8098, "ln": -122.485, "s": 0.9, "h": 25, "stat": "active", "dtg": "21.73", "dstat": "Racing"}, {"ts": 1528831200, "lt": 47.812, "ln": -122.4835, "s": 0.9, "h": 25, "stat": "active", "dtg": "21.73", "dstat": "Racing"}, {"ts": 1528831800, "lt": 47.8142, "ln": -122.4819, "s": 0.9, "h": 25, "stat": "active", "dtg": "21.73", "dstat": "Racing"}, {"ts": 1528832400, "lt": 47.818, "ln": -122.483, "s": 1.4, "h": 349, "stat": "active", "dtg": "20.88", "dstat": "Racing"}, {"ts": 1528833000, "lt": 47.8223, "ln": -122.4857, "s": 1.7, "h": 337, "stat": "active", "dtg": "20.61", "dstat": "Racing"}, {"ts": 1528833600, "lt": 47.8275, "ln": -122.4892, "s": 2, "h": 335, "stat": "active", "dtg": "20.26", "dstat": "Racing"}, {"ts": 1528834200, "lt": 47.8322, "ln": -122.4916, "s": 1.8, "h": 341, "stat": "active", "dtg": "19.98", "dstat": "Racing"}, {"ts": 1528834800, "lt": 47.8365, "ln": -122.4964, "s": 1.9, "h": 323, "stat": "active", "dtg": "19.65", "dstat": "Racing"}, {"ts": 1528835400, "lt": 47.8421, "ln": -122.5003, "s": 2.2, "h": 334, "stat": "active", "dtg": "19.30", "dstat": "Racing"}, {"ts": 1528836000, "lt": 47.8478, "ln": -122.5046, "s": 2.3, "h": 333, "stat": "active", "dtg": "18.90", "dstat": "Racing"}, {"ts": 1528836600, "lt": 47.8521, "ln": -122.5068, "s": 1.6, "h": 341, "stat": "active", "dtg": "18.64", "dstat": "Racing"}, {"ts": 1528837200, "lt": 47.8572, "ln": -122.5086, "s": 1.9, "h": 346, "stat": "active", "dtg": "18.35", "dstat": "Racing"}, {"ts": 1528837800, "lt": 47.8624, "ln": -122.5135, "s": 2.2, "h": 327, "stat": "active", "dtg": "17.96", "dstat": "Racing"}, {"ts": 1528838400, "lt": 47.8623, "ln": -122.5136, "s": 0.1, "h": 215, "stat": "active", "dtg": "17.96", "dstat": "Racing"}, {"ts": 1528839000, "lt": 47.8628, "ln": -122.5134, "s": 0.2, "h": 12, "stat": "active", "dtg": "17.95", "dstat": "Racing"}, {"ts": 1528839600, "lt": 47.8695, "ln": -122.5129, "s": 2.4, "h": 2, "stat": "active", "dtg": "17.61", "dstat": "Racing"}, {"ts": 1528840200, "lt": 47.8778, "ln": -122.5129, "s": 3, "h": 0, "stat": "active", "dtg": "17.21", "dstat": "Racing"}, {"ts": 1528840800, "lt": 47.8838, "ln": -122.5147, "s": 2.2, "h": 348, "stat": "active", "dtg": "16.89", "dstat": "Racing"}, {"ts": 1528841400, "lt": 47.8913, "ln": -122.5181, "s": 2.9, "h": 342, "stat": "active", "dtg": "16.44", "dstat": "Racing"}, {"ts": 1528842000, "lt": 47.8992, "ln": -122.5212, "s": 2.9, "h": 345, "stat": "active", "dtg": "15.99", "dstat": "Racing"}, {"ts": 1528842600, "lt": 47.9084, "ln": -122.5238, "s": 3.4, "h": 348, "stat": "active", "dtg": "15.48", "dstat": "Racing"}, {"ts": 1528843200, "lt": 47.9123, "ln": -122.5277, "s": 1.7, "h": 326, "stat": "active", "dtg": "15.15", "dstat": "Racing"}, {"ts": 1528843800, "lt": 47.9123, "ln": -122.5277, "s": 0, "h": 159, "stat": "active", "dtg": "15.15", "dstat": "Racing"}, {"ts": 1528844400, "lt": 47.9126, "ln": -122.5287, "s": 0.3, "h": 297, "stat": "active", "dtg": "15.15", "dstat": "Racing"}, {"ts": 1528845000, "lt": 47.9161, "ln": -122.5382, "s": 2.6, "h": 298, "stat": "active", "dtg": "15.15", "dstat": "Racing"}, {"ts": 1528845600, "lt": 47.9195, "ln": -122.5478, "s": 2.6, "h": 298, "stat": "active", "dtg": "15.15", "dstat": "Racing"}, {"ts": 1528846200, "lt": 47.9229, "ln": -122.5573, "s": 2.6, "h": 298, "stat": "active", "dtg": "15.15", "dstat": "Racing"}, {"ts": 1528846800, "lt": 47.9263, "ln": -122.5669, "s": 2.6, "h": 298, "stat": "active", "dtg": "15.15", "dstat": "Racing"}, {"ts": 1528847400, "lt": 47.9298, "ln": -122.5764, "s": 2.6, "h": 298, "stat": "active", "dtg": "15.15", "dstat": "Racing"}, {"ts": 1528848000, "lt": 47.9332, "ln": -122.586, "s": 2.6, "h": 298, "stat": "active", "dtg": "15.15", "dstat": "Racing"}, {"ts": 1528848600, "lt": 47.9366, "ln": -122.5955, "s": 2.6, "h": 298, "stat": "active", "dtg": "15.15", "dstat": "Racing"}, {"ts": 1528849200, "lt": 47.9401, "ln": -122.605, "s": 2.6, "h": 298, "stat": "active", "dtg": "15.15", "dstat": "Racing"}, {"ts": 1528849800, "lt": 47.9435, "ln": -122.6146, "s": 2.6, "h": 298, "stat": "active", "dtg": "15.15", "dstat": "Racing"}, {"ts": 1528850400, "lt": 47.9466, "ln": -122.6253, "s": 2.8, "h": 293, "stat": "active", "dtg": "11.41", "dstat": "Racing"}, {"ts": 1528851000, "lt": 47.951, "ln": -122.6352, "s": 2.9, "h": 303, "stat": "active", "dtg": "11.02", "dstat": "Racing"}, {"ts": 1528851600, "lt": 47.9563, "ln": -122.6435, "s": 2.8, "h": 312, "stat": "active", "dtg": "10.54", "dstat": "Racing"}, {"ts": 1528852200, "lt": 47.9625, "ln": -122.6506, "s": 2.8, "h": 322, "stat": "active", "dtg": "10.19", "dstat": "Racing"}, {"ts": 1528852800, "lt": 47.9707, "ln": -122.6593, "s": 3.6, "h": 324, "stat": "active", "dtg": "9.57", "dstat": "Racing"}, {"ts": 1528853400, "lt": 47.9778, "ln": -122.6662, "s": 3.1, "h": 326, "stat": "active", "dtg": "9.08", "dstat": "Racing"}, {"ts": 1528854000, "lt": 47.9856, "ln": -122.6739, "s": 3.4, "h": 326, "stat": "active", "dtg": "8.53", "dstat": "Racing"}, {"ts": 1528854600, "lt": 47.9929, "ln": -122.6819, "s": 3.3, "h": 323, "stat": "active", "dtg": "8.00", "dstat": "Racing"}, {"ts": 1528855200, "lt": 47.9987, "ln": -122.6886, "s": 2.6, "h": 322, "stat": "active", "dtg": "7.53", "dstat": "Racing"}, {"ts": 1528855800, "lt": 48.0034, "ln": -122.6937, "s": 2.1, "h": 324, "stat": "active", "dtg": "7.20", "dstat": "Racing"}, {"ts": 1528856400, "lt": 48.0076, "ln": -122.6994, "s": 2, "h": 317, "stat": "active", "dtg": "6.85", "dstat": "Racing"}, {"ts": 1528857000, "lt": 48.0121, "ln": -122.7052, "s": 2.2, "h": 319, "stat": "active", "dtg": "6.57", "dstat": "Racing"}, {"ts": 1528857600, "lt": 48.0177, "ln": -122.7129, "s": 2.7, "h": 317, "stat": "active", "dtg": "6.19", "dstat": "Racing"}, {"ts": 1528858200, "lt": 48.023, "ln": -122.7212, "s": 2.8, "h": 313, "stat": "active", "dtg": "5.79", "dstat": "Racing"}, {"ts": 1528858800, "lt": 48.0322, "ln": -122.7319, "s": 4.2, "h": 321, "stat": "active", "dtg": "5.28", "dstat": "Racing"}, {"ts": 1528859400, "lt": 48.0404, "ln": -122.7384, "s": 3.4, "h": 332, "stat": "active", "dtg": "4.74", "dstat": "Racing"}, {"ts": 1528860000, "lt": 48.0506, "ln": -122.7454, "s": 4, "h": 335, "stat": "active", "dtg": "4.08", "dstat": "Racing"}, {"ts": 1528860600, "lt": 48.0609, "ln": -122.7512, "s": 4, "h": 339, "stat": "active", "dtg": "3.49", "dstat": "Racing"}, {"ts": 1528861200, "lt": 48.0715, "ln": -122.7551, "s": 3.9, "h": 346, "stat": "active", "dtg": "2.86", "dstat": "Racing"}, {"ts": 1528861800, "lt": 48.0785, "ln": -122.7555, "s": 2.5, "h": 357, "stat": "active", "dtg": "2.41", "dstat": "Racing"}, {"ts": 1528862400, "lt": 48.0864, "ln": -122.7546, "s": 2.9, "h": 4, "stat": "active", "dtg": "1.91", "dstat": "Racing"}, {"ts": 1528863000, "lt": 48.0948, "ln": -122.7532, "s": 3.1, "h": 6, "stat": "active", "dtg": "1.41", "dstat": "Racing"}, {"ts": 1528863600, "lt": 48.1025, "ln": -122.7528, "s": 2.8, "h": 1, "stat": "active", "dtg": "0.93", "dstat": "Racing"}, {"ts": 1528864200, "lt": 48.1101, "ln": -122.7531, "s": 2.8, "h": 358, "stat": "active", "dtg": "0.47", "dstat": "Racing"}], "meta": {"source": "db", "next_update": 0, "query_timestamp": 1572798600}}