{"error": null, "message": "Requested completed successfully.", "payload": [{"ts": 1433422800, "lt": 48.1242, "ln": -122.7296, "s": 1.8, "h": 46, "stat": "active", "dstat": "Active"}, {"ts": 1433423700, "lt": 48.127, "ln": -122.7257, "s": 0.5, "h": 21, "stat": "active", "dstat": "Active"}, {"ts": 1433424600, "lt": 48.1286, "ln": -122.7262, "s": 0.4, "h": 323, "stat": "active", "dstat": "Active"}, {"ts": 1433425500, "lt": 48.1303, "ln": -122.7283, "s": 0.6, "h": 258, "stat": "active", "dstat": "Active"}, {"ts": 1433426400, "lt": 48.1311, "ln": -122.7328, "s": 0.9, "h": 301, "stat": "finished", "dstat": "DNF"}, {"ts": 1433427300, "lt": 48.134, "ln": -122.7373, "s": 1, "h": 273, "stat": "finished", "dstat": "DNF"}, {"ts": 1433428200, "lt": 48.1351, "ln": -122.7438, "s": 1.2, "h": 289, "stat": "finished", "dstat": "DSQ"}, {"ts": 1433429100, "lt": 48.1387, "ln": -122.7486, "s": 1.2, "h": 322, "stat": "active", "dstat": "Racing"}, {"ts": 1433430000, "lt": 48.1436, "ln": -122.7513, "s": 1.4, "h": 352, "stat": "active", "dstat": "Racing"}, {"ts": 1433430900, "lt": 48.1485, "ln": -122.7614, "s": 1, "h": 263, "stat": "active", "dstat": "Racing"}, {"ts": 1433431800, "lt": 48.1457, "ln": -122.7622, "s": 1, "h": 161, "stat": "active", "dstat": "Racing"}, {"ts": 1433432700, "lt": 48.1434, "ln": -122.7604, "s": 0, "h": 45, "stat": "active", "dstat": "Racing"}, {"ts": 1433433600, "lt": 48.1433, "ln": -122.7604, "s": 0, "h": 333, "stat": "active", "dstat": "Racing"}, {"ts": 1433434500, "lt": 48.1434, "ln": -122.7604, "s": 0, "h": 180, "stat": "active", "dstat": "Racing"}, {"ts": 1433435400, "lt": 48.1434, "ln": -122.7604, "s": 0, "h": 0, "stat": "active", "dstat": "Racing"}, {"ts": 1433436300, "lt": 48.1434, "ln": -122.7604, "s": 0, "h": 233, "stat": "active", "dstat": "Racing"}, {"ts": 1433437200, "lt": 48.1433, "ln": -122.7604, "s": 0, "h": 157, "stat": "active", "dstat": "Racing"}, {"ts": 1433438100, "lt": 48.1433, "ln": -122.7604, "s": 0, "h": 157, "stat": "active", "dstat": "Racing"}, {"ts": 1433439000, "lt": 48.1433, "ln": -122.7604, "s": 0, "h": 157, "stat": "active", "dstat": "Racing"}, {"ts": 1433439900, "lt": 48.1433, "ln": -122.7603, "s": 0, "h": 157, "stat": "active", "dstat": "Racing"}, {"ts": 1433440800, "lt": 48.1432, "ln": -122.7603, "s": 0, "h": 157, "stat": "active", "dstat": "Racing"}, {"ts": 1433441700, "lt": 48.1432, "ln": -122.7603, "s": 0, "h": 157, "stat": "active", "dstat": "Racing"}, {"ts": 1433442600, "lt": 48.1432, "ln": -122.7603, "s": 0, "h": 157, "stat": "active", "dstat": "Racing"}, {"ts": 1433443500, "lt": 48.1432, "ln": -122.7603, "s": 0, "h": 157, "stat": "active", "dstat": "Racing"}, {"ts": 1433444400, "lt": 48.1432, "ln": -122.7603, "s": 0, "h": 157, "stat": "active", "dstat": "Racing"}, {"ts": 1433445300, "lt": 48.1287, "ln": -122.7556, "s": 3.6, "h": 167, "stat": "active", "dstat": "Racing"}, {"ts": 1433446200, "lt": 48.1223, "ln": -122.7536, "s": 2.6, "h": 167, "stat": "active", "dstat": "Racing"}, {"ts": 1433447100, "lt": 48.1206, "ln": -122.7535, "s": 1.9, "h": 168, "stat": "active", "dstat": "Racing"}, {"ts": 1433448000, "lt": 48.1191, "ln": -122.7531, "s": 0, "h": 201, "stat": "active", "dstat": "Racing"}, {"ts": 1433448900, "lt": 48.1192, "ln": -122.7533, "s": 0.1, "h": 332, "stat": "active", "dstat": "Racing"}]}