{"error": null, "message": "Requested completed successfully.", "payload": [{"ts": 1496922300, "lt": 48.1155, "ln": -122.7501, "s": 0.1, "h": 103, "stat": "active", "dstat": "Active"}, {"ts": 1496923200, "lt": 48.1152, "ln": -122.7507, "s": 0.1, "h": 210, "stat": "active", "dstat": "Active"}, {"ts": 1496924100, "lt": 48.1159, "ln": -122.7496, "s": 1.6, "h": 22, "stat": "active", "dstat": "Active"}, {"ts": 1496925000, "lt": 48.1385, "ln": -122.7544, "s": 10.8, "h": 346, "stat": "active", "dstat": "Active"}, {"ts": 1496925900, "lt": 48.153, "ln": -122.7653, "s": 1.8, "h": 303, "stat": "active", "dstat": "Active"}, {"ts": 1496926800, "lt": 48.1576, "ln": -122.7765, "s": 2.5, "h": 300, "stat": "active", "dstat": "Active"}, {"ts": 1496927700, "lt": 48.1609, "ln": -122.791, "s": 5.8, "h": 344, "stat": "active", "dstat": "Active"}, {"ts": 1496928600, "lt": 48.1857, "ln": -122.7933, "s": 6.4, "h": 8, "stat": "active", "dstat": "Active"}, {"ts": 1496929500, "lt": 48.1648, "ln": -122.8068, "s": 6, "h": 138, "stat": "active", "dstat": "Active"}, {"ts": 1496930400, "lt": 48.1548, "ln": -122.8106, "s": 5.1, "h": 266, "stat": "active", "dstat": "Active"}, {"ts": 1496931300, "lt": 48.1536, "ln": -122.8426, "s": 5.1, "h": 266, "stat": "active", "dstat": "Active"}, {"ts": 1496932200, "lt": 48.1535, "ln": -122.8402, "s": 5.6, "h": 87, "stat": "active", "dstat": "Active"}, {"ts": 1496933100, "lt": 48.1562, "ln": -122.8257, "s": 18.4, "h": 279, "stat": "active", "dstat": "Active"}, {"ts": 1496934000, "lt": 48.1604, "ln": -122.9116, "s": 14.4, "h": 275, "stat": "active", "dstat": "Active"}, {"ts": 1496934900, "lt": 48.1912, "ln": -122.9516, "s": 9.9, "h": 328, "stat": "active", "dstat": "Active"}, {"ts": 1496935800, "lt": 48.2087, "ln": -122.9728, "s": 2, "h": 289, "stat": "active", "dstat": "Active"}, {"ts": 1496936700, "lt": 48.2111, "ln": -122.9813, "s": 1.4, "h": 293, "stat": "active", "dstat": "Active"}, {"ts": 1496937600, "lt": 48.2135, "ln": -122.9893, "s": 1.4, "h": 293, "stat": "active", "dstat": "Active"}, {"ts": 1496938500, "lt": 48.2158, "ln": -122.9974, "s": 1.4, "h": 293, "stat": "active", "dstat": "Active"}, {"ts": 1496939400, "lt": 48.2182, "ln": -123.0055, "s": 1.4, "h": 293, "stat": "active", "dstat": "Active"}, {"ts": 1496940300, "lt": 48.2206, "ln": -123.0135, "s": 1.4, "h": 293, "stat": "active", "dstat": "Active"}, {"ts": 1496941200, "lt": 48.2229, "ln": -123.0216, "s": 1.4, "h": 293, "stat": "active", "dstat": "Active"}, {"ts": 1496942100, "lt": 48.2253, "ln": -123.0296, "s": 1.4, "h": 293, "stat": "active", "dstat": "Active"}, {"ts": 1496943000, "lt": 48.2276, "ln": -123.0377, "s": 1.4, "h": 293, "stat": "active", "dstat": "Active"}, {"ts": 1496943900, "lt": 48.23, "ln": -123.0457, "s": 1.4, "h": 293, "stat": "active", "dstat": "Active"}, {"ts": 1496944800, "lt": 48.2323, "ln": -123.0538, "s": 1.4, "h": 293, "stat": "active", "dstat": "Active"}, {"ts": 1496945700, "lt": 48.2346, "ln": -123.0651, "s": 3, "h": 279, "stat": "active", "dstat": "Active"}, {"ts": 1496946600, "lt": 48.2368, "ln": -123.0721, "s": 1.4, "h": 293, "stat": "active", "dstat": "Active"}, {"ts": 1496947500, "lt": 48.2155, "ln": -123.0126, "s": 13, "h": 120, "stat": "active", "dstat": "Active"}, {"ts": 1496948400, "lt": 48.1813, "ln": -122.9359, "s": 15.8, "h": 125, "stat": "active", "dstat": "Active"}, {"ts": 1496949300, "lt": 48.1568, "ln": -122.8475, "s": 17.5, "h": 106, "stat": "active", "dstat": "Active"}, {"ts": 1496950200, "lt": 48.1353, "ln": -122.78, "s": 9.3, "h": 123, "stat": "active", "dstat": "Active"}]}